{
	"diagnostic.virtualTextCurrentLineOnly": false,
	"diagnostic.virtualText": true,
	"snippets.priority": 1,
	"suggest.completionItemKindLabels": {
		"method": "  ",
		"function": "  ",
		"variable": "[]",
		"field": "  ",
		"typeParameter": "<>",
		"constant": "  ",
		"class": " פּ ",
		"interface": " 蘒",
		"struct": "  ",
		"event": "  ",
		"operator": "  ",
		"module": "  ",
		"property": "  ",
		"enum": " 練",
		"reference": "  ",
		"keyword": "  ",
		"file": "  ",
		"folder": " ﱮ ",
		"color": "  ",
		"unit": " 塞 ",
		"snippet": "  ",
		"text": "  ",
		"constructor": "  ",
		"value": "  ",
		"enumMember": "  "
	},
	"languageserver": {
		"ccls": {
			"command": "ccls",
			"filetypes": ["c", "cpp", "objc", "objcpp"],
			"rootPatterns": [
				".ccls",
				"compile_commands.json",
				".vim/",
				".git/",
				".hg/"
			],
			"initializationOptions": {
				"cache": {
					"directory": "/tmp/ccls"
				}
			}
		}
	},
	"coc.preferences.formatOnSaveFiletypes": [
		"json",
		"cpp",
		"typescript",
		"javascript",
		"go"
	],
	"coc.preferences.hoverTarget": "float",
	"coc.preferences.snippetStatusText": "SNIP",
	"coc.preferences.enableMessageDialog": true,
	"coc.preferences.bracketEnterImprove": true,
	"prettier.bracketSpacing": true,
	"coc.preferences.useQuickfixForLocations": true,
	"coc.preferences.snippets.enable": true,
	"signature.enable": true,
	"signature.preferShownAbove": true,
	"prettier.useTabs": true,
	"prettier.tabWidth": 4,
	"snippets.ultisnips.enable": true,
	"snippets.snipmate.enable": false,
	"snippets.ultisnips.directories": [
		"~/.config/nvim/plugged/vim-snippets/UltiSnips"
	],
	"explorer.icon.enableNerdfont": true,
	"explorer.quitOnOpen": true,
	"codeLens.enable": true,
	"java.home": "/home/vinmoraes/.jdks/openjdk-15.0.1",
	"java.referencesCodeLens.enabled": true
}
